kevent/__init__.py
kevent/event.py
kevent/dispatcher/__init__.py
kevent/dispatcher/types.py
kevent/dispatcher/simple/__init__.py
kevent/dispatcher/simple/callback.py
kevent/dispatcher/simple/constants.py
kevent/dispatcher/simple/subscribers.py
kevent/dispatcher/simple/dispatcher/__init__.py
kevent/dispatcher/simple/dispatcher/config.py
kevent/dispatcher/simple/dispatcher/dispatcher.py
kevent/dispatcher/simple/dispatcher/interface.py
kevent/test/__init__.py
kevent/test/test.py
kevent-0.1.4.1.dist-info/licenses/LICENSE
kevent-0.1.4.1.dist-info/METADATA
kevent-0.1.4.1.dist-info/WHEEL
kevent-0.1.4.1.dist-info/top_level.txt
kevent-0.1.4.1.dist-info/RECORD
